hierarchicalsoftmax/__init__.py
hierarchicalsoftmax/dotexporter.py
hierarchicalsoftmax/examples/__marimo__/cifar.html
hierarchicalsoftmax/examples/__marimo__/cifar.ipynb
hierarchicalsoftmax/examples/cifar.py
hierarchicalsoftmax/inference.py
hierarchicalsoftmax/layers.py
hierarchicalsoftmax/loss.py
hierarchicalsoftmax/metrics.py
hierarchicalsoftmax/nodes.py
hierarchicalsoftmax/tensors.py
hierarchicalsoftmax/treedict.py
hierarchicalsoftmax-1.4.4.dist-info/LICENSE
hierarchicalsoftmax-1.4.4.dist-info/METADATA
hierarchicalsoftmax-1.4.4.dist-info/WHEEL
hierarchicalsoftmax-1.4.4.dist-info/entry_points.txt
hierarchicalsoftmax-1.4.4.dist-info/RECORD
