Metadata-Version: 2.3
Name: hierarchicalsoftmax
Version: 1.4.4
Summary: A Hierarchical Softmax Framework for PyTorch.
License: Apache-2.0
Keywords: pytorch,softmax
Author: Robert Turnbull
Author-email: robert.turnbull@unimelb.edu.au
Requires-Python: >=3.10,<4.0
Classifier: Intended Audience :: Science/Research
Classifier: License :: OSI Approved :: Apache Software License
Classifier: Programming Language :: Python :: 3
Classifier: Programming Language :: Python :: 3.10
Classifier: Programming Language :: Python :: 3.11
Classifier: Programming Language :: Python :: 3.12
Classifier: Programming Language :: Python :: 3.13
Classifier: Topic :: Scientific/Engineering :: Artificial Intelligence
Classifier: Topic :: Software Development :: Libraries :: Python Modules
Provides-Extra: examples
Requires-Dist: anytree (>=2.8.0)
Requires-Dist: attrs (>=25.3.0)
Requires-Dist: graphviz (>=0.20.3)
Requires-Dist: plotly (>=5.0.0)
Requires-Dist: rich (>=10.16.1)
Requires-Dist: scikit-learn (>=1.1.1)
Requires-Dist: torch (>=1.10.2)
Requires-Dist: torchmetrics (>=1.4.0.post0)
Requires-Dist: typer (>=0.15.4)
Project-URL: Documentation, https://rbturnbull.github.io/hierarchicalsoftmax/
Project-URL: Homepage, https://github.com/rbturnbull/hierarchicalsoftmax
Project-URL: Repository, https://github.com/rbturnbull/hierarchicalsoftmax
